lightdht/__init__.py
lightdht/client.py
lightdht/server.py
lightdht/tools.py
lightdht-0.0.1.dist-info/LICENSE
lightdht-0.0.1.dist-info/METADATA
lightdht-0.0.1.dist-info/WHEEL
lightdht-0.0.1.dist-info/top_level.txt
lightdht-0.0.1.dist-info/RECORD
