Metadata-Version: 2.1
Name: lightdht
Version: 0.0.1
Summary: LightDHT is a lightweight distributed hash table for decentralized networks and applications.
Home-page: https://gitlab.com/XmlEntity/lightdht
Author: Xml Entity
Author-email: lightdht@riseup.net
License: UNKNOWN
Project-URL: Bug Tracker, https://gitlab.com/XmlEntity/lightdht/-/issues
Platform: UNKNOWN
Classifier: Programming Language :: Python :: 3
Classifier: License :: OSI Approved :: MIT License
Classifier: Operating System :: OS Independent
Requires-Python: >=3.6
License-File: LICENSE
